query_params/__init__.py
query_params/apps.py
query_params/static/query_params/js/query_params.js
query_params/static/query_params/js/query_params.tests.html
query_params/static/query_params/js/query_params.tests.js
query_params/templatetags/__init__.py
query_params/templatetags/query_params_tags.py
query_params/tests/__init__.py
query_params/tests/test_templatetags.py
django_query_params-1.0.0.dist-info/AUTHORS.md
django_query_params-1.0.0.dist-info/LICENSE.md
django_query_params-1.0.0.dist-info/METADATA
django_query_params-1.0.0.dist-info/WHEEL
django_query_params-1.0.0.dist-info/top_level.txt
django_query_params-1.0.0.dist-info/RECORD
